dbf_to_sqlite/__init__.py
dbf_to_sqlite/cli.py
dbf_to_sqlite-0.1.dist-info/LICENSE
dbf_to_sqlite-0.1.dist-info/METADATA
dbf_to_sqlite-0.1.dist-info/WHEEL
dbf_to_sqlite-0.1.dist-info/entry_points.txt
dbf_to_sqlite-0.1.dist-info/top_level.txt
dbf_to_sqlite-0.1.dist-info/RECORD
