Metadata-Version: 2.1
Name: dbf-to-sqlite
Version: 0.1
Summary: CLCLI tool for converting DBF files (dBase, FoxPro etc) to SQLite
Home-page: https://github.com/simonw/dbf-to-sqlite
Author: Simon Willison
License: Apache License, Version 2.0
Platform: UNKNOWN
Classifier: Development Status :: 3 - Alpha
Classifier: Intended Audience :: Developers
Classifier: Intended Audience :: Science/Research
Classifier: Intended Audience :: End Users/Desktop
Classifier: Topic :: Database
Classifier: License :: OSI Approved :: Apache Software License
Classifier: Programming Language :: Python :: 3.6
Classifier: Programming Language :: Python :: 3.7
Requires-Dist: dbf (==0.97.11)
Requires-Dist: click
Requires-Dist: sqlite-utils
